README.rst
setup.py
opps_sdk/__init__.py
opps_sdk/common_util.py
opps_sdk/opps_client.py
opps_sdk.egg-info/PKG-INFO
opps_sdk.egg-info/SOURCES.txt
opps_sdk.egg-info/dependency_links.txt
opps_sdk.egg-info/requires.txt
opps_sdk.egg-info/top_level.txt
opps_sdk/core/__init__.py
opps_sdk/core/api_request.py
opps_sdk/core/log_util.py
opps_sdk/core/param_handler.py
opps_sdk/core/rsa_utils.py
opps_sdk/module/__init__.py
opps_sdk/module/card.py
opps_sdk/module/cert.py
opps_sdk/module/mer_config.py
opps_sdk/module/opps_tools.py
opps_sdk/module/request_tools.py
opps_sdk/module/online/__init__.py
opps_sdk/module/online/card_payment.py
opps_sdk/module/online/scan_payment.py
tests/__init__.py
tests/conftest.py
tests/test_payment.py