Metadata-Version: 1.1
Name: opps-sdk
Version: 0.0.9
Summary: common utils of opps sdk
Home-page: https://www.opps.tech/
Author: opps developers
Author-email: hi@opps.tech
License: UNKNOWN
Platform: UNKNOWN
Classifier: Development Status :: 4 - Beta
Classifier: Intended Audience :: Developers
Classifier: Topic :: Software Development :: Build Tools
Classifier: License :: OSI Approved :: MIT License
Classifier: Programming Language :: Python
Classifier: Programming Language :: Python :: 3.5
Classifier: Programming Language :: Python :: 3.6
Classifier: Programming Language :: Python :: 3.7
